insigen/__init__.py
insigen/insigen.py
insigen/scraper.py
insigen/test.py
insigen/Data/__init__.py
insigen/Data/embeds.pickle
insigen/Data/td.json
insigen/Data/topics.pickle
insigen/Data/wiki.csv
insigen-0.1.8.dist-info/LICENSE
insigen-0.1.8.dist-info/METADATA
insigen-0.1.8.dist-info/WHEEL
insigen-0.1.8.dist-info/top_level.txt
insigen-0.1.8.dist-info/RECORD
