Metadata-Version: 2.1
Name: insigen
Version: 0.1.8
Summary: Generates Insights from text pieces such as Documents or Articles
Home-page: https://github.com/4RCAN3/insigen
Author: Aaryan Tyagi
Author-email: Aaryan Tyagi <tyagiaaryan00@gmail.com>
License: Apache License
Project-URL: Homepage, https://github.com/4RCAN3/insigen
Project-URL: Issues, https://github.com/4RCAN3/insigen/issues
Keywords: NLP,Topic Modelling,Text analysis,Summary Extraction,Keyword Extraction
Classifier: License :: OSI Approved :: Apache Software License
Classifier: Programming Language :: Python
Classifier: Programming Language :: Python :: 3
Requires-Python: >=3.11
License-File: LICENSE
Requires-Dist: pandas
Requires-Dist: numpy
Requires-Dist: gensim
Requires-Dist: wordcloud
Requires-Dist: nltk
Requires-Dist: sentence-transformers
Requires-Dist: networkx
Requires-Dist: PyPDF2
Requires-Dist: beautifulsoup4
Requires-Dist: requests
Requires-Dist: tomli; python_version < "3.11"
